kusosort/__init__.py
kusosort/_kusosort_impl.cp312-win_amd64.pyd
kusosort/cpp/CMakeLists.txt
kusosort/cpp/kusosort.cpp
kusosort-0.2.1.dist-info/METADATA
kusosort-0.2.1.dist-info/WHEEL
kusosort-0.2.1.dist-info/licenses/LICENSE
kusosort-0.2.1.dist-info/RECORD
