Metadata-Version: 2.2
Name: kusosort
Version: 0.2.1
Summary: A collection of joke sorting algorithms implemented in C++ for Python.
Author-Email: Your Name <you@example.com>
License: MIT License
Classifier: Programming Language :: Python :: 3
Classifier: License :: OSI Approved :: MIT License
Classifier: Operating System :: OS Independent
Classifier: Topic :: Software Development :: Libraries :: Python Modules
Classifier: Intended Audience :: Developers
Classifier: Programming Language :: C++
Project-URL: Homepage, https://github.com/KIIIIT00/kusosort
Project-URL: Bug Tracker, https://github.com/KIIIIT00/kusosort/issues
Requires-Python: >=3.8
Provides-Extra: dev
Requires-Dist: pytest; extra == "dev"
